CHANGES.txt
LICENSE.txt
MANIFEST.in
README.rst
setup.py
DQuery.egg-info/PKG-INFO
DQuery.egg-info/SOURCES.txt
DQuery.egg-info/dependency_links.txt
DQuery.egg-info/requires.txt
DQuery.egg-info/top_level.txt
bin/dquery
bin/dquery_php_var_json
dquery/__init__.py
dquery/application.py
dquery/json_settings.php
dquery/lib.py
dquery/settings.py
dquery/xml.py
dquery/xpath.py
dquery/commands/__init__.py
dquery/commands/module_directories_dquery_command.py
dquery/commands/module_info_dquery_command.py
dquery/commands/multisite_xml_dquery_command.py
dquery/commands/sites_dquery_command.py
dquery/commands/status_report_dquery_command.py
dquery/commands/theme_directories_dquery_command.py
dquery/commands/xpath_dquery_command.py
dquery/formatters/__init__.py
dquery/formatters/json_dquery_formatter.py
dquery/formatters/pipe_dquery_formatter.py
dquery/formatters/yaml_dquery_formatter.py
dquery/test/__init__.py