Metadata-Version: 1.0
Name: DQuery
Version: 0.1.0-rc5
Summary: Drupal multisite query-tool.
Home-page: http://pypi.python.org/pypi/DQuery/
Author: David Gustafsson
Author-email: david.gustafsson@xelera.se
License: GPL
Download-URL: https://github.com/david-xelera/dquery/tarball/master
Keywords: drupal
Platform: UNKNOWN
Classifier: Development Status :: 4 - Beta
Classifier: Environment :: Console
Classifier: Intended Audience :: Developers
Classifier: Intended Audience :: System Administrators
Classifier: License :: OSI Approved :: MIT License
Classifier: License :: OSI Approved :: GNU General Public License v2 (GPLv2)
Classifier: Operating System :: POSIX
Classifier: Programming Language :: PHP
Classifier: Programming Language :: Python
Classifier: Topic :: Software Development :: Quality Assurance
Classifier: Topic :: System :: Systems Administration
Classifier: Topic :: Utilities
